boris/__init__.py
boris/__main__.py
boris/about.py
boris/add_modifier.py
boris/add_modifier_ui.py
boris/advanced_event_filtering.py
boris/behav_coding_map_creator.py
boris/behavior_binary_table.py
boris/behaviors_coding_map.py
boris/boris_cli.py
boris/cmd_arguments.py
boris/coding_pad.py
boris/config.py
boris/config_file.py
boris/connections.py
boris/converters.py
boris/converters_ui.py
boris/cooccurence.py
boris/core.py
boris/core_qrc.py
boris/core_ui.py
boris/db_functions.py
boris/dev.py
boris/dialog.py
boris/duration_widget.py
boris/edit_event.py
boris/edit_event_ui.py
boris/event_operations.py
boris/events_cursor.py
boris/events_snapshots.py
boris/exclusion_matrix.py
boris/export_events.py
boris/export_observation.py
boris/external_processes.py
boris/geometric_measurement.py
boris/gui_utilities.py
boris/image_overlay.py
boris/import_observations.py
boris/ipc_mpv.py
boris/irr.py
boris/latency.py
boris/measurement_widget.py
boris/media_file.py
boris/menu_options.py
boris/modifier_coding_map_creator.py
boris/modifiers_coding_map.py
boris/mpv.py
boris/mpv2.py
boris/observation.py
boris/observation_operations.py
boris/observation_ui.py
boris/observations_list.py
boris/otx_parser.py
boris/param_panel.py
boris/param_panel_ui.py
boris/player_dock_widget.py
boris/plot_data_module.py
boris/plot_events.py
boris/plot_events_rt.py
boris/plot_spectrogram_rt.py
boris/plot_waveform_rt.py
boris/plugins.py
boris/preferences.py
boris/preferences_ui.py
boris/project.py
boris/project_functions.py
boris/project_import_export.py
boris/project_ui.py
boris/qrc_boris.py
boris/qrc_boris5.py
boris/select_modifiers.py
boris/select_observations.py
boris/select_subj_behav.py
boris/state_events.py
boris/subjects_pad.py
boris/synthetic_time_budget.py
boris/time_budget_functions.py
boris/time_budget_widget.py
boris/transitions.py
boris/utilities.py
boris/version.py
boris/video_equalizer.py
boris/video_equalizer_ui.py
boris/video_operations.py
boris/view_df.py
boris/view_df_ui.py
boris_behav_obs-9.7.15.dist-info/licenses/LICENSE.TXT
boris_behav_obs-9.7.15.dist-info/METADATA
boris_behav_obs-9.7.15.dist-info/WHEEL
boris_behav_obs-9.7.15.dist-info/entry_points.txt
boris_behav_obs-9.7.15.dist-info/top_level.txt
boris_behav_obs-9.7.15.dist-info/RECORD
